umbi/__init__.py
umbi/__main__.py
umbi/logger.py
umbi/version.py
umbi/ats/__init__.py
umbi/ats/annotation.py
umbi/ats/explicit_ats.py
umbi/ats/model_info.py
umbi/binary/__init__.py
umbi/binary/bitvectors.py
umbi/binary/common.py
umbi/binary/floats.py
umbi/binary/integers.py
umbi/binary/intervals.py
umbi/binary/jsons.py
umbi/binary/rationals.py
umbi/binary/sequences.py
umbi/binary/strings.py
umbi/binary/structs.py
umbi/binary/utils.py
umbi/datatypes/__init__.py
umbi/datatypes/common_type.py
umbi/datatypes/csr.py
umbi/datatypes/interval.py
umbi/datatypes/json.py
umbi/datatypes/struct.py
umbi/io/__init__.py
umbi/io/tar.py
umbi/io/umb.py
umbi/io/umb_ats_converter.py
umbi/io/index/__init__.py
umbi/io/index/annotations.py
umbi/io/index/file_data.py
umbi/io/index/json_schema.py
umbi/io/index/model_data.py
umbi/io/index/transition_system.py
umbi/io/index/umb_index.py
umbi/io/index/variable_valuations.py
umbi-0.1.24.dist-info/licenses/LICENSE
umbi-0.1.24.dist-info/METADATA
umbi-0.1.24.dist-info/WHEEL
umbi-0.1.24.dist-info/entry_points.txt
umbi-0.1.24.dist-info/top_level.txt
umbi-0.1.24.dist-info/RECORD
