Metadata-Version: 2.4
Name: umbi
Version: 0.1.24
Summary: Library for input/output of transition systems in a unified Markov binary (UMB) format.
Author-email: Roman Andriushchenko <roman.andriu@gmail.com>
License: MIT License
Project-URL: Homepage, https://github.com/randriu/umbi
Requires-Python: >=3.11
License-File: LICENSE
Requires-Dist: click
Requires-Dist: marshmallow
Requires-Dist: marshmallow_oneofschema
Requires-Dist: bitstring
Provides-Extra: dev
Requires-Dist: pytest; extra == "dev"
Requires-Dist: pip-tools; extra == "dev"
Requires-Dist: black; extra == "dev"
Requires-Dist: isort; extra == "dev"
Requires-Dist: toml-sort; extra == "dev"
Requires-Dist: twine; extra == "dev"
Requires-Dist: bump-my-version; extra == "dev"
Dynamic: license-file
